PipelineProcessor/__init__.py
PipelineProcessor/base_clases.py
PipelineProcessor/BasicFunctionRepository.py
PipelineProcessor/BasicStreamFunctionRepository.py
PipelineProcessor/commands.py
PipelineProcessor/FileHandler.py
PipelineProcessor/Processor.py
PipelineProcessor/StreamFunctionRepository.py
PipelineProcessor/YmlConfigLoader.py
pipelineprocessor-0.1.1.dist-info/entry_points.txt
pipelineprocessor-0.1.1.dist-info/METADATA
pipelineprocessor-0.1.1.dist-info/WHEEL
pipelineprocessor-0.1.1.dist-info/RECORD
