Metadata-Version: 2.1
Name: PipelineProcessor
Version: 0.1.1
Summary: 
Author: Pritam Chowdhury
Author-email: pritamchowdhury19798@gmail.com
Requires-Python: >=3.11,<4.0
Classifier: Programming Language :: Python :: 3
Classifier: Programming Language :: Python :: 3.11
Classifier: Programming Language :: Python :: 3.12
Requires-Dist: pyyaml (>=6.0.1,<7.0.0)
Requires-Dist: requests (>=2.32.3,<3.0.0)
Requires-Dist: typer (>=0.12.0,<0.13.0)
Requires-Dist: yml (>=0.0.1,<0.0.2)
